django_upyun/__init__.py
django_upyun/backends.py
django_upyun/defaults.py
django_upyun-1.0.1.dist-info/METADATA
django_upyun-1.0.1.dist-info/RECORD
django_upyun-1.0.1.dist-info/WHEEL
django_upyun-1.0.1.dist-info/top_level.txt
