Metadata-Version: 2.1
Name: django-upyun
Version: 1.0.1
Summary: Django 又拍云存储插件
Home-page: https://gitee.com/enlangs/django-upyun-storage
Author: UNKNOWN
Author-email: UNKNOWN
License: UNKNOWN
Platform: UNKNOWN
Classifier: Development Status :: 5 - Production/Stable
Classifier: Intended Audience :: Developers
Classifier: License :: OSI Approved :: MIT License
Classifier: Operating System :: OS Independent
Classifier: Programming Language :: Python :: 3.6
Classifier: Framework :: Django
Requires-Dist: django (>=2.0)
Requires-Dist: upyun (>=2.5.1)
